flyteplugins/union/__init__.py
flyteplugins/union/cli/__init__.py
flyteplugins/union/cli/api_key.py
flyteplugins/union/internal/__init__.py
flyteplugins/union/internal/common/list_pb2.py
flyteplugins/union/internal/common/list_pb2.pyi
flyteplugins/union/internal/common/list_pb2_grpc.py
flyteplugins/union/internal/identity/app_definition_pb2.py
flyteplugins/union/internal/identity/app_definition_pb2.pyi
flyteplugins/union/internal/identity/app_definition_pb2_grpc.py
flyteplugins/union/internal/identity/app_payload_pb2.py
flyteplugins/union/internal/identity/app_payload_pb2.pyi
flyteplugins/union/internal/identity/app_payload_pb2_grpc.py
flyteplugins/union/internal/identity/app_service_pb2.py
flyteplugins/union/internal/identity/app_service_pb2.pyi
flyteplugins/union/internal/identity/app_service_pb2_grpc.py
flyteplugins/union/internal/identity/enums_pb2.py
flyteplugins/union/internal/identity/enums_pb2.pyi
flyteplugins/union/internal/identity/enums_pb2_grpc.py
flyteplugins/union/internal/validate/__init__.py
flyteplugins/union/internal/validate/validate/__init__.py
flyteplugins/union/internal/validate/validate/validate_pb2.py
flyteplugins/union/internal/validate/validate/validate_pb2_grpc.py
flyteplugins/union/remote/__init__.py
flyteplugins/union/remote/_api_key.py
flyteplugins/union/utils/__init__.py
flyteplugins/union/utils/auth.py
flyteplugins_union-0.1.0.dist-info/licenses/LICENSE
flyteplugins_union-0.1.0.dist-info/METADATA
flyteplugins_union-0.1.0.dist-info/WHEEL
flyteplugins_union-0.1.0.dist-info/entry_points.txt
flyteplugins_union-0.1.0.dist-info/top_level.txt
flyteplugins_union-0.1.0.dist-info/RECORD
