Metadata-Version: 2.4
Name: flyteplugins-union
Version: 0.1.0
Summary: Union SDK - Proprietary extensions for Flyte
Author-email: unionai <info@union.ai>
Project-URL: Homepage, https://www.union.ai/
Project-URL: Documentation, https://docs.union.ai/
Classifier: Intended Audience :: Science/Research
Classifier: Intended Audience :: Developers
Classifier: License :: Other/Proprietary License
Classifier: Programming Language :: Python :: 3.10
Classifier: Programming Language :: Python :: 3.11
Classifier: Programming Language :: Python :: 3.12
Classifier: Programming Language :: Python :: 3.13
Classifier: Topic :: Scientific/Engineering
Classifier: Topic :: Software Development
Requires-Python: >=3.10
License-File: LICENSE
Requires-Dist: flyte<2.1.0,>=2.0.0b26
Requires-Dist: flyteidl2>=2.0.0a15
Requires-Dist: rich-click>=1.8.0
Dynamic: license-file
